<ezstream>
    <url>http://YOUR-ICECAST-SERVER:8000/axia</url>
    
    <sourcepassword>hackme</sourcepassword>
    <format>MP3</format>
    <filename>stdin</filename>
    <stream_once>1</stream_once>

    <svrinfoname>Awesome Stream Name</svrinfoname>
    <svrinfourl>http://awesomestream.org</svrinfourl>
    <svrinfogenre>Any</svrinfogenre>
    <svrinfodescription>This is my web stream straight from Livewire!</svrinfodescription>

    <!--
      Prohibit the server to advertise the stream on a public YP directory:
     -->
    <svrinfopublic>1</svrinfopublic>
</ezstream>
